{
  "main": {
    "id": "ede43c93fa647663",
    "type": "split",
    "children": [
      {
        "id": "78730f8f8123ae21",
        "type": "tabs",
        "children": [
          {
            "id": "2287b37805ca0f15",
            "type": "leaf",
            "state": {
              "type": "markdown",
              "state": {
                "file": "dsa/python/graph/DFS/soln/tree/dfs.md",
                "mode": "source",
                "source": false
              }
            }
          },
          {
            "id": "0e5b21f38ddf903d",
            "type": "leaf",
            "state": {
              "type": "markdown",
              "state": {
                "file": "dsa/python/graph/DFS/soln/graph/2d.md",
                "mode": "source",
                "source": false
              }
            }
          },
          {
            "id": "a7e2c97aaf79a393",
            "type": "leaf",
            "state": {
              "type": "markdown",
              "state": {
                "file": "dsa/python/graph/DFS/soln/notes.md",
                "mode": "source",
                "source": false
              }
            }
          }
        ],
        "currentTab": 1
      }
    ],
    "direction": "vertical"
  },
  "left": {
    "id": "d4029cfd1ff501b3",
    "type": "split",
    "children": [
      {
        "id": "e816bdde1e5f7ba6",
        "type": "tabs",
        "children": [
          {
            "id": "0fc21ab84329c7e6",
            "type": "leaf",
            "state": {
              "type": "file-explorer",
              "state": {
                "sortOrder": "alphabetical"
              }
            }
          },
          {
            "id": "a92172e4224c3266",
            "type": "leaf",
            "state": {
              "type": "search",
              "state": {
                "query": "obsidia",
                "matchingCase": false,
                "explainSearch": false,
                "collapseAll": false,
                "extraContext": false,
                "sortOrder": "alphabetical"
              }
            }
          },
          {
            "id": "071c10325addc8b5",
            "type": "leaf",
            "state": {
              "type": "bookmarks",
              "state": {}
            }
          }
        ]
      }
    ],
    "direction": "horizontal",
    "width": 357.5
  },
  "right": {
    "id": "9c35d27a5aece4b5",
    "type": "split",
    "children": [
      {
        "id": "fa410d830a6dbf4b",
        "type": "tabs",
        "children": [
          {
            "id": "2622e60b4fc70c65",
            "type": "leaf",
            "state": {
              "type": "backlink",
              "state": {
                "file": "dsa/python/graph/DFS/soln/graph/2d.md",
                "collapseAll": false,
                "extraContext": false,
                "sortOrder": "alphabetical",
                "showSearch": false,
                "searchQuery": "",
                "backlinkCollapsed": false,
                "unlinkedCollapsed": true
              }
            }
          },
          {
            "id": "09f7e2e7d6a64a1c",
            "type": "leaf",
            "state": {
              "type": "outgoing-link",
              "state": {
                "file": "dsa/python/graph/DFS/soln/graph/2d.md",
                "linksCollapsed": false,
                "unlinkedCollapsed": true
              }
            }
          },
          {
            "id": "77105771f9934e3c",
            "type": "leaf",
            "state": {
              "type": "tag",
              "state": {
                "sortOrder": "frequency",
                "useHierarchy": true
              }
            }
          },
          {
            "id": "9186f4104557354e",
            "type": "leaf",
            "state": {
              "type": "outline",
              "state": {
                "file": "dsa/python/graph/DFS/soln/graph/2d.md"
              }
            }
          }
        ]
      }
    ],
    "direction": "horizontal",
    "width": 300
  },
  "left-ribbon": {
    "hiddenItems": {
      "switcher:Open quick switcher": false,
      "graph:Open graph view": false,
      "canvas:Create new canvas": false,
      "daily-notes:Open today's daily note": false,
      "templates:Insert template": false,
      "command-palette:Open command palette": false,
      "markdown-importer:Open format converter": false,
      "workspaces:Manage workspace layouts": false,
      "zk-prefixer:Create new unique note": false,
      "audio-recorder:Start/stop recording": false,
      "random-note:Open random note": false
    }
  },
  "active": "0e5b21f38ddf903d",
  "lastOpenFiles": [
    "dsa/python/graph/DFS/DFS.md",
    "dsa/python/graph/DFS/soln/tree/dfs.md",
    "dsa/python/graph/DFS/soln/notes.md",
    "dsa/python/graph/DFS/soln/graph/2d.md",
    "dsa/python/slack/__init__.md",
    "dsa/python/slack/soln/basic stack.md",
    "dsa/python/slack/soln",
    "dsa/python/slack",
    "dsa/python/graph/DFS/soln/graph/basic.md",
    "dsa/python/graph/BFS.md",
    "dsa/python/graph/DFS/soln/tree/basic.md",
    "dsa/python/graph/DFS/soln/graph",
    "dsa/python/graph/DFS/soln/tre. /basic.md",
    "dsa/python/graph/DFS/soln/basic.md",
    "dsa/python/graph/DFS/soln/tre. ",
    "dsa/python/graph/DFS/soln/tree",
    "dsa/python/graph/DFS/soln/t.md",
    "dsa/python/graph/qns/Find All Leaves of a Binary Tree.md",
    "dsa/python/graph/DFS/soln",
    "dsa/python/graph/DFS",
    "dsa/python/appln.md",
    "dsa/python/sliding windows/type1/counter.md",
    "dsa/python/sliding windows/type1/basics.md",
    "Pasted image 20240620090926.png",
    "Pasted image 20240620090812.png",
    "Pasted image 20240620090733.png",
    "Pasted image 20240620090635.png",
    "Pasted image 20240620090555.png",
    "Pasted image 20240620090501.png",
    "Pasted image 20240620090401.png",
    "Pasted image 20240620090339.png",
    "Pasted image 20240620090300.png",
    "Pasted image 20240620090200.png",
    "dsa/python/sliding windows/__init__.md",
    "dsa/python/sliding windows/type1/ba.md",
    "dsa/python/sliding windows/type1",
    "dsa/python/greedy/__init__.md",
    "dsa/python/dp/__init__.md",
    "dsa/python/dp/questions/memorization (top down approach)/part 1 (1d dp).md",
    "dsa/python/dp/dp algorithym.md",
    "dsa/python/graph/intro.md",
    "dsa/python/dp/questions/memorization (top down approach)/part 2 (2d  dp).md",
    "dsa/python/dp/questions/tabulation/part 2 min max.md",
    "dsa/python/dp/questions/memorization (top down approach)/part 3 complex dp.md",
    "dsa/python/two pointers",
    "dsa/python/sliding windows",
    "Untitled 2.canvas",
    "Untitled 1.canvas",
    "Untitled.canvas"
  ]
}