{
  "main": {
    "id": "ede43c93fa647663",
    "type": "split",
    "children": [
      {
        "id": "f66fef6eae7640f4",
        "type": "tabs",
        "children": [
          {
            "id": "6da133e81948486e",
            "type": "leaf",
            "state": {
              "type": "empty",
              "state": {}
            }
          }
        ]
      }
    ],
    "direction": "vertical"
  },
  "left": {
    "id": "d4029cfd1ff501b3",
    "type": "split",
    "children": [
      {
        "id": "e816bdde1e5f7ba6",
        "type": "tabs",
        "children": [
          {
            "id": "0fc21ab84329c7e6",
            "type": "leaf",
            "state": {
              "type": "file-explorer",
              "state": {
                "sortOrder": "alphabetical"
              }
            }
          },
          {
            "id": "a92172e4224c3266",
            "type": "leaf",
            "state": {
              "type": "search",
              "state": {
                "query": "obsidia",
                "matchingCase": false,
                "explainSearch": false,
                "collapseAll": false,
                "extraContext": false,
                "sortOrder": "alphabetical"
              }
            }
          },
          {
            "id": "071c10325addc8b5",
            "type": "leaf",
            "state": {
              "type": "bookmarks",
              "state": {}
            }
          }
        ]
      }
    ],
    "direction": "horizontal",
    "width": 300
  },
  "right": {
    "id": "9c35d27a5aece4b5",
    "type": "split",
    "children": [
      {
        "id": "fa410d830a6dbf4b",
        "type": "tabs",
        "children": [
          {
            "id": "2622e60b4fc70c65",
            "type": "leaf",
            "state": {
              "type": "backlink",
              "state": {
                "collapseAll": false,
                "extraContext": false,
                "sortOrder": "alphabetical",
                "showSearch": false,
                "searchQuery": "",
                "backlinkCollapsed": false,
                "unlinkedCollapsed": true
              }
            }
          },
          {
            "id": "09f7e2e7d6a64a1c",
            "type": "leaf",
            "state": {
              "type": "outgoing-link",
              "state": {
                "linksCollapsed": false,
                "unlinkedCollapsed": true
              }
            }
          },
          {
            "id": "77105771f9934e3c",
            "type": "leaf",
            "state": {
              "type": "tag",
              "state": {
                "sortOrder": "frequency",
                "useHierarchy": true
              }
            }
          },
          {
            "id": "9186f4104557354e",
            "type": "leaf",
            "state": {
              "type": "outline",
              "state": {}
            }
          }
        ]
      }
    ],
    "direction": "horizontal",
    "width": 300,
    "collapsed": true
  },
  "left-ribbon": {
    "hiddenItems": {
      "switcher:Open quick switcher": false,
      "graph:Open graph view": false,
      "canvas:Create new canvas": false,
      "daily-notes:Open today's daily note": false,
      "templates:Insert template": false,
      "command-palette:Open command palette": false,
      "markdown-importer:Open format converter": false,
      "workspaces:Manage workspace layouts": false,
      "zk-prefixer:Create new unique note": false,
      "audio-recorder:Start/stop recording": false,
      "random-note:Open random note": false
    }
  },
  "active": "6da133e81948486e",
  "lastOpenFiles": [
    "interview/14+ days spreek(12-26+)/sde/4th 10/snapchat.md",
    "interview/14+ days spreek(12-26+)/sde/4th 10/instagram.md",
    "interview/14+ days spreek(12-26+)/sde/4th 10/facebook.md",
    "interview/14+ days spreek(12-26+)/sde/4th 10/jira.md",
    "interview/14+ days spreek(12-26+)/sde/4th 10/App-store.md",
    "interview/14+ days spreek(12-26+)/sde/4th 10/Design Amazon E-commerce.md",
    "interview/14+ days spreek(12-26+)/sde/4th 10/offline caching system for Ecommerce platform.md",
    "interview/14+ days spreek(12-26+)/sde/3rd 10/Amazon Locker.md",
    "interview/14+ days spreek(12-26+)/sde/4th 10",
    "interview/14+ days spreek(12-26+)/sde/Untitled.md",
    "interview/14+ days spreek(12-26+)/sde/3rd 10/google doc.md",
    "interview/14+ days spreek(12-26+)/sde/3rd 10/game platform.md",
    "interview/14+ days spreek(12-26+)/sde/3rd 10/calendly.md",
    "interview/14+ days spreek(12-26+)/sde/3rd 10/music player application.md",
    "interview/14+ days spreek(12-26+)/sde/3rd 10/AirBNB.md",
    "interview/14+ days spreek(12-26+)/sde/3rd 10/distributed LRU Cache.md",
    "interview/14+ days spreek(12-26+)/sde/3rd 10/recommendation system.md",
    "interview/14+ days spreek(12-26+)/sde/3rd 10/Paypal.md",
    "interview/14+ days spreek(12-26+)/sde/3rd 10/google map.md",
    "interview/14+ days spreek(12-26+)/sde/2nd 10/zoom.md",
    "interview/14+ days spreek(12-26+)/sde/3rd 10",
    "interview/14+ days spreek(12-26+)/sde/2nd 10/twitter.md",
    "interview/14+ days spreek(12-26+)/sde/2nd 10/Dropbox or Google Drive.md",
    "interview/14+ days spreek(12-26+)/sde/2nd 10/Lookahead system.md",
    "interview/14+ days spreek(12-26+)/sde/2nd 10/quora.md",
    "interview/14+ days spreek(12-26+)/sde/first 10/whatsapp.md",
    "interview/14+ days spreek(12-26+)/sde/2nd 10/Design Cricbuzz.md",
    "interview/14+ days spreek(12-26+)/sde/2nd 10/Design a Notification service.md",
    "interview/14+ days spreek(12-26+)/sde/2nd 10",
    "interview/14+ days spreek(12-26+)/sde/first 10",
    "interview/14+ days spreek(12-26+)/sde",
    "interview/14+ days spreek(12-26+)/aws",
    "Untitled 2.canvas",
    "interview/14+ days spreek(12-26+)/aws_resources.json",
    "interview/14+ days spreek(12-26+)/aws_resources.json.txt",
    "interview/14+ days spreek(12-26+)/New Text Document.txt",
    "interview/14+ days spreek(12-26+)",
    "Pasted image 20230812155758.png",
    "Pasted image 20230812155741.png",
    "Pasted image 20230812155656.png",
    "Pasted image 20230812155550.png",
    "jrUBAF7.png",
    "Pasted image 20230723030726.png",
    "Pasted image 20230723025926.png",
    "Pasted image 20230723024340.png",
    "Pasted image 20230723023844.png",
    "Pasted image 20230723023654.png",
    "Untitled 1.canvas",
    "Untitled.canvas"
  ]
}